nmrtools/ccpcsv2dat.py
nmrtools/comp2plot.py
nmrtools/comp2pse.py
nmrtools/dat2comp.py
nmrtools/dat2series.py
nmrtools/peaks2dat.py
nmrtools/series2plot.py
nmrtools/utils.py
nmrtools_pkg-0.1.1.data/scripts/nmrtools
nmrtools_pkg-0.1.1.dist-info/LICENSE
nmrtools_pkg-0.1.1.dist-info/METADATA
nmrtools_pkg-0.1.1.dist-info/WHEEL
nmrtools_pkg-0.1.1.dist-info/top_level.txt
nmrtools_pkg-0.1.1.dist-info/RECORD
