Metadata-Version: 2.1
Name: nmrtools-pkg
Version: 0.1.1
Summary: UNKNOWN
Home-page: https://github.com/synthaze/nmrtools
Author: Florian Malard, PhD
Author-email: florian.malard@gmail.com
License: UNKNOWN
Project-URL: Bug Tracker, https://github.com/synthaze/nmrtools/issues
Platform: UNKNOWN
Classifier: Programming Language :: Python :: 3
Classifier: License :: OSI Approved :: GNU General Public License v3 (GPLv3)
Classifier: Operating System :: OS Independent
Requires-Python: >=3.7
Requires-Dist: Pillow (==11.2.1)
Requires-Dist: fpdf (==1.7.2)
Requires-Dist: matplotlib (==3.3.4)
Requires-Dist: numpy (==1.19.5)
Requires-Dist: pybasics (==0.3.3)
Requires-Dist: pymol (==0.1.0)
Requires-Dist: scipy (==1.6.0)
Requires-Dist: setuptools (==52.0.0)
